rwas/__init__.py
rwas/columns.py
rwas/read_config.py
rwas/rwas.py
rwas/services.py
rwas-0.0.2.dist-info/LICENSE
rwas-0.0.2.dist-info/METADATA
rwas-0.0.2.dist-info/WHEEL
rwas-0.0.2.dist-info/top_level.txt
rwas-0.0.2.dist-info/RECORD
