Metadata-Version: 2.1
Name: rwas
Version: 0.0.2
Summary: pip install rwas
Home-page: https://github.com/erickdsama/rwas_library
Author: Erick Samaniego
Author-email: erickdsama@gmail.com
License: MIT
Keywords: rwas,whatsapp,bot,rest
Platform: UNKNOWN
